[
  {
    "nom": "GHANNEM Dhouha",
    "specialité": "Gynécologie obstétrique",
    "adresse": "avenue Zayatine Haffouz 3130",
    "telephone": "21202270",
    "ville": "kairouan"
  },
  {
    "nom": "ZRAFI Wael Salem",
    "specialité": "Radiothérapie carcinologique",
    "adresse": "cité Zitouna Mansoura  kairouan  3100",
    "telephone": "52229648",
    "ville": "kairouan"
  },
  {
    "nom": "KEFI Naissen",
    "specialité": "Ophtalmologie",
    "adresse": "rue Ibn El Aghlab Diar El Yosr  kairouan  3100",
    "telephone": "31575657",
    "ville": "kairouan"
  },
  {
    "nom": "BEN ZAYED Chefia",
    "specialité": "Pédiatrie",
    "adresse": "Complexe Médical Echifa lotissement ouled Souidène Bouhajla 3180",
    "telephone": "99365917",
    "ville": "kairouan"
  },
  {
    "nom": "KALBOUSSI Takwa",
    "specialité": "Médecine générale",
    "adresse": "ragada  kairouan  3100",
    "telephone": "28175675",
    "ville": "kairouan"
  },
  {
    "nom": "GHAFFARA Sahbi",
    "specialité": "Ophtalmologie",
    "adresse": "Rue ennahassine Kairouan 3100",
    "telephone": "77288292",
    "ville": "kairouan"
  },
  {
    "nom": "AYDI Maher",
    "specialité": "Chirurgie orthopédique et traumatologique",
    "adresse": "Complexe Elchifa Lot Awled Souidene Bouhajla 3180",
    "telephone": "25049150",
    "ville": "kairouan"
  },
  {
    "nom": "GHANNEM Mohamed Achraf",
    "specialité": "Médecine générale",
    "adresse": "avenue Habib Thameur Sbikha 3130",
    "telephone": "21188177",
    "ville": "kairouan"
  },
  {
    "nom": "CHERIF Wassef",
    "specialité": "Gynécologie obstétrique",
    "adresse": "Avenue abi zomaa el balaoui Kairouan 3100",
    "telephone": "93383883",
    "ville": "kairouan"
  },
  {
    "nom": "AFLI Hatem",
    "specialité": "Médecine générale",
    "adresse": "avenue Ali Zouaoui Haffouz 3116",
    "telephone": "77356986",
    "ville": "kairouan"
  },
  {
    "nom": "GABBOUJ HAJJI Asma",
    "specialité": "Médecine interne",
    "adresse": "Avenue ibn el aghleb complexe ibn zohr  kairouan  3100",
    "telephone": "77271555",
    "ville": "kairouan"
  },
  {
    "nom": "ZRIBI Abdellatif",
    "specialité": "Radiothérapie carcinologique",
    "adresse": "Avenue ibnou al aghlab Kairouan 3100",
    "telephone": "96353387",
    "ville": "kairouan"
  },
  {
    "nom": "MOKNI Sahbi",
    "specialité": "Médecine générale",
    "adresse": "Menzel m'hiri Menzel M'hiri 3114",
    "telephone": "58076925",
    "ville": "kairouan"
  },
  {
    "nom": "JAOUADI Houssem",
    "specialité": "Médecine générale",
    "adresse": "avenue de la liberté route principale  cherarda  3116",
    "telephone": "77268110",
    "ville": "kairouan"
  },
  {
    "nom": "BOUALLEGUE Riadh",
    "specialité": "Médecine générale",
    "adresse": "14 rue abbassia Kairouan 3100",
    "telephone": "77231400",
    "ville": "kairouan"
  },
  {
    "nom": "DIMASSI CHAKROUN Zouhour",
    "specialité": "Gynécologie obstétrique",
    "adresse": "Rue soukeina bent houssine imm. Basli Kairouan 3100",
    "telephone": "77238777",
    "ville": "kairouan"
  },
  {
    "nom": "TAAMALLAH Mohamed Habib",
    "specialité": "Médecine générale",
    "adresse": "Kairouan 3100",
    "telephone": "77231141",
    "ville": "kairouan"
  },
  {
    "nom": "EL OUESLATI Aymen",
    "specialité": "Chirurgie orthopédique et traumatologique",
    "adresse": "Rue ali belhaouane Kairouan 3100",
    "telephone": "77232744",
    "ville": "kairouan"
  },
  {
    "nom": "AISSA Mohamed Anouar",
    "specialité": "Médecine générale",
    "adresse": "avenue Beit El Hekma cité el Moez el mansoura Kairouan 3100",
    "telephone": "77355444",
    "ville": "kairouan"
  },
  {
    "nom": "SOUA Nabil",
    "specialité": "Chirurgie générale",
    "adresse": "Immeuble dar ettabib rue mouaouia ibn hodayj 3100",
    "telephone": "77303333",
    "ville": "kairouan"
  },
  {
    "nom": "MEJRI Mariem",
    "specialité": "Médecine générale",
    "adresse": "Hajeb El Ayoun 3160",
    "telephone": "77371535",
    "ville": "kairouan"
  },
  {
    "nom": "GAFSI Maher",
    "specialité": "Chirurgie urologique",
    "adresse": "Rue moawia ibn hodaij imm dar itabib 3100",
    "telephone": "77304428",
    "ville": "kairouan"
  },
  {
    "nom": "MELLASSI HAMMAMI Refka",
    "specialité": "Gynécologie obstétrique",
    "adresse": "Avenue Ibn El Aghleb Kairouan 3100",
    "telephone": "77237449",
    "ville": "kairouan"
  },
  {
    "nom": "CHERMITI Zaineb",
    "specialité": "Médecine générale",
    "adresse": "Avenue habib bourguiba 3120",
    "telephone": "95302998",
    "ville": "kairouan"
  },
  {
    "nom": "GHANNEM Karim",
    "specialité": "Cardiologie",
    "adresse": "22, avenue abi zomaa el balaoui 3100",
    "telephone": "23959261",
    "ville": "kairouan"
  },
  {
    "nom": "HARRATHI Monia",
    "specialité": "Médecine générale",
    "adresse": "Hopital régional kasserine Kasserine 1200",
    "telephone": "21802253",
    "ville": "kairouan"
  },
  {
    "nom": "CHATTI CHEBAANE Ines",
    "specialité": "Neurologie",
    "adresse": "Avenue ibn el aghlab Kairouan 3100",
    "telephone": "77274400",
    "ville": "kairouan"
  },
  {
    "nom": "SAADA Wajdi",
    "specialité": "Psychiatrie",
    "adresse": "Avenue Ibn El Aghleb  kairouan  3100",
    "telephone": "22879273",
    "ville": "kairouan"
  },
  {
    "nom": "MARZOUK JENAYAH Ibtissem Thouraya",
    "specialité": "Médecine générale",
    "adresse": "15 avenue Ibn Rakik  kairouan  3100",
    "telephone": "77235393",
    "ville": "kairouan"
  },
  {
    "nom": "RHIF Houssem",
    "specialité": "Médecine du travail",
    "adresse": "Avenue habib bourguiba",
    "telephone": "99614622",
    "ville": "kairouan"
  },
  {
    "nom": "SAKKA ROUIS Kamel",
    "specialité": "Médecine générale",
    "adresse": "Dar djamia 3132",
    "telephone": "20403176",
    "ville": "kairouan"
  },
  {
    "nom": "SAKKA Hedi",
    "specialité": "Chirurgie orthopédique et traumatologique",
    "adresse": "Rue ibrahim ibn el aghleb Chebika 3100",
    "telephone": "94637000",
    "ville": "kairouan"
  },
  {
    "nom": "FERID Zied",
    "specialité": "Ophtalmologie",
    "adresse": "Avenue abou zomaa balaoui 3100",
    "telephone": "77228129",
    "ville": "kairouan"
  },
  {
    "nom": "MSAKNI Tarek",
    "specialité": "Endocrinologie",
    "adresse": "Rue ibn el aghleb immeuble ibn sina 3100",
    "telephone": "77233333",
    "ville": "kairouan"
  },
  {
    "nom": "AMICHE HSOUMI Sondes",
    "specialité": "Médecine générale",
    "adresse": "hôpital nasrallah Nasrallah 3170",
    "telephone": "50533503",
    "ville": "kairouan"
  },
  {
    "nom": "MESSAOUDI Haithem",
    "specialité": "Médecine générale",
    "adresse": "Aouled messaoud",
    "telephone": "77256270",
    "ville": "kairouan"
  },
  {
    "nom": "GHARBI Mohamed",
    "specialité": "Chirurgie urologique",
    "adresse": "Avenue abi zamaa el balaoui",
    "telephone": "77227752",
    "ville": "kairouan"
  },
  {
    "nom": "SAIDI Souhaiel",
    "specialité": "Gynécologie obstétrique",
    "adresse": "Rue abou zomaa el balaoui cité essaied",
    "telephone": "77227324",
    "ville": "kairouan"
  },
  {
    "nom": "HAJJI Hassene",
    "specialité": "Chirurgie générale",
    "adresse": "96, avenue abi zamaa al balaoui 3100",
    "telephone": "77235535",
    "ville": "kairouan"
  },
  {
    "nom": "OTHMANE Jihène",
    "specialité": "Gynécologie obstétrique",
    "adresse": "Rue ibn el jazzar",
    "telephone": "77228060",
    "ville": "kairouan"
  },
  {
    "nom": "JAOUADI Soufièn",
    "specialité": "Chirurgie générale",
    "adresse": "Rue de la république riwak errabii",
    "telephone": "98960955",
    "ville": "kairouan"
  },
  {
    "nom": "ROMDHANI KNAISSI Jawaher",
    "specialité": "Médecine générale",
    "adresse": "adresse l'hôpital local de chebika 3121",
    "telephone": "73296868",
    "ville": "kairouan"
  },
  {
    "nom": "CHARFEDDINE Lotfi",
    "specialité": "Pédiatrie",
    "adresse": "Rue mouaouia ibn houdaije (hajjem)",
    "telephone": "77304900",
    "ville": "kairouan"
  },
  {
    "nom": "SEFSEFI Soufiène",
    "specialité": "Médecine générale",
    "adresse": "Avenue 7 novembre",
    "telephone": "77266580",
    "ville": "kairouan"
  },
  {
    "nom": "DHAHRI Warda",
    "specialité": "Médecine générale",
    "adresse": "Av.Ali Zouaoui imm.Abdallah Louati",
    "telephone": "77371218",
    "ville": "kairouan"
  },
  {
    "nom": "CHANGUEL BEN AMOR Lilia",
    "specialité": "Dermatologie",
    "adresse": "Hôpital ibn el jazzar 3100",
    "telephone": "77226300",
    "ville": "kairouan"
  },
  {
    "nom": "BEN MOUSSA Fehmi",
    "specialité": "Biologie médicale option hématologie",
    "adresse": "Galerie le printemps av. Abou zomaa el balaoui",
    "telephone": "77227292",
    "ville": "kairouan"
  },
  {
    "nom": "CHAFAI GHARBI Rim",
    "specialité": "Carcinologie médicale",
    "adresse": "rue Ibn El Aghleb  kairouan  3100",
    "telephone": "77273200",
    "ville": "kairouan"
  },
  {
    "nom": "AMRI Asma",
    "specialité": "Médecine générale",
    "adresse": "N° 5, rue landaria",
    "telephone": "77229799",
    "ville": "kairouan"
  },
  {
    "nom": "DAOUD Khaled",
    "specialité": "Pneumologie",
    "adresse": "Rue ibn el aghleb",
    "telephone": "77273222",
    "ville": "kairouan"
  },
  {
    "nom": "TURKI Elyes",
    "specialité": "Médecine légale",
    "adresse": "Hôpital ibn el jazzar  kairouan  3100",
    "telephone": "77226300",
    "ville": "kairouan"
  },
  {
    "nom": "SASSI Raja",
    "specialité": "Biologie médicale option hématologie",
    "adresse": "Hôpital ibn el jazzar",
    "telephone": "77226300",
    "ville": "kairouan"
  },
  {
    "nom": "ABENE AMRI Olfa",
    "specialité": "Médecine générale",
    "adresse": "Centre régional de la médecine et des sciences du sport",
    "telephone": "77238270",
    "ville": "kairouan"
  },
  {
    "nom": "TRABELSI Amel",
    "specialité": "Anatomie et cytologie pathologique",
    "adresse": "Avenue ibn al aghleb immeuble ibn sina n°107",
    "telephone": "77273999",
    "ville": "kairouan"
  },
  {
    "nom": "JEBENIANI Sofiane",
    "specialité": "Médecine générale",
    "adresse": "31 rue de la victoire",
    "telephone": "77237437",
    "ville": "kairouan"
  },
  {
    "nom": "TRIFI Ahmed",
    "specialité": "Médecine générale",
    "adresse": "Route de la jeunesse",
    "telephone": "77371482",
    "ville": "kairouan"
  },
  {
    "nom": "MLAYEH Souheil",
    "specialité": "Médecine légale",
    "adresse": "HOPITAL REGIONAL IBN EL JAZZAR KAIROUAN Rue Ibn Jazzar 3100, KAIROUAN 3100",
    "telephone": "73221411",
    "ville": "kairouan"
  },
  {
    "nom": "BOUFARES Ramzi",
    "specialité": "Chirurgie orthopédique et traumatologique",
    "adresse": "Rue ibrahim ibn el aghleb",
    "telephone": "53072004",
    "ville": "kairouan"
  },
  {
    "nom": "BEN HADJ EL BECHIR BOUMIZA Amel",
    "specialité": "Dermatologie",
    "adresse": "Avenue Ibn El Aghleb  kairouan  3100",
    "telephone": "77272466",
    "ville": "kairouan"
  },
  {
    "nom": "MARZOUGUI Aâhed",
    "specialité": "Médecine générale",
    "adresse": "Rue ibn khaldoun",
    "telephone": "77360186",
    "ville": "kairouan"
  },
  {
    "nom": "MESKINI Mongi",
    "specialité": "Médecine générale",
    "adresse": "67, rue de la république",
    "telephone": "77356922",
    "ville": "kairouan"
  },
  {
    "nom": "MASKHI Salah",
    "specialité": "Cardiologie",
    "adresse": "Complexe médical  ibn zohr  Kairouan 3100",
    "telephone": "77270166",
    "ville": "kairouan"
  },
  {
    "nom": "BEN MANSOUR MESKHI Jaata",
    "specialité": "Gastro-entérologie",
    "adresse": "HOPITAL REGIONAL IBN EL JAZZAR KAIROUAN Rue Ibn Jazzar 3100, KAIROUAN 3100",
    "telephone": "77270166",
    "ville": "kairouan"
  },
  {
    "nom": "M'BAREK Chaouki",
    "specialité": "Gastro-entérologie",
    "adresse": "Rue ibn alaghlab immeuble ibn sina",
    "telephone": "77273666",
    "ville": "kairouan"
  },
  {
    "nom": "KHARRAT Issam Eddin",
    "specialité": "Médecine générale",
    "adresse": "Hôpital ibn el jazzar 3130",
    "telephone": "77226300",
    "ville": "kairouan"
  },
  {
    "nom": "BSILA Monia",
    "specialité": "Médecine générale",
    "adresse": "hôpital Ibn Jazzar 3100",
    "telephone": "77237162",
    "ville": "kairouan"
  },
  {
    "nom": "MSEKNI Sahbi",
    "specialité": "Médecine générale",
    "adresse": "11, rue abou zoomaa el balaoui",
    "telephone": "77264321",
    "ville": "kairouan"
  },
  {
    "nom": "BOULIFI Fatteh",
    "specialité": "Chirurgie générale",
    "adresse": "208, rue ibn sina",
    "telephone": "77227474",
    "ville": "kairouan"
  },
  {
    "nom": "SAIDANI Mohamed Salah",
    "specialité": "Anesthésie réanimation",
    "adresse": "Polyclinique hamda laouani",
    "telephone": "77271444",
    "ville": "kairouan"
  },
  {
    "nom": "FERJAOUI HEDHLI Lobna",
    "specialité": "Médecine générale",
    "adresse": "Av.Hadika Oueslatia 3120",
    "telephone": "77351600",
    "ville": "kairouan"
  },
  {
    "nom": "SALEM Braiek",
    "specialité": "Chirurgie urologique",
    "adresse": "HOPITAL REGIONAL IBN EL JAZZAR KAIROUAN Rue Ibn Jazzar 3100, KAIROUAN 3100",
    "telephone": "77226300",
    "ville": "kairouan"
  },
  {
    "nom": "SEBRI Abdelwaheb",
    "specialité": "Médecine générale",
    "adresse": "7,rue el moêz ben badis",
    "telephone": "77235568",
    "ville": "kairouan"
  },
  {
    "nom": "NAIFER Radhouane",
    "specialité": "Gynécologie obstétrique",
    "adresse": "Rue moawiya ibn houdai imm. Dar tabib el hajjem",
    "telephone": "77302617",
    "ville": "kairouan"
  },
  {
    "nom": "BEN KILANI Farid",
    "specialité": "Médecine générale",
    "adresse": "Bir alloussffan  cherarda  3145",
    "telephone": "98656339",
    "ville": "kairouan"
  },
  {
    "nom": "KAROUI Samir",
    "specialité": "Chirurgie urologique",
    "adresse": "Avenue ibrahim ibn el aghleb imm ibn sina etage 2 app 15",
    "telephone": "77234444",
    "ville": "kairouan"
  },
  {
    "nom": "BARHOUMI Aboulkacem",
    "specialité": "Médecine générale",
    "adresse": "17, rue telemcen étage 1",
    "telephone": "98689060",
    "ville": "kairouan"
  },
  {
    "nom": "DEBBECH Noureddine",
    "specialité": "Médecine générale",
    "adresse": "HOPITAL REGIONAL ZAGHOUAN Avenue de l'Environnement 1100, ZAGHOUAN 1100",
    "telephone": "98631315",
    "ville": "kairouan"
  },
  {
    "nom": "KACEM KAROUI Sonia",
    "specialité": "Ophtalmologie",
    "adresse": "Rue Ibrahim ibn el aghleb  kairouan  3100",
    "telephone": "20006710",
    "ville": "kairouan"
  },
  {
    "nom": "GDHAMI Sofiène",
    "specialité": "Médecine générale",
    "adresse": "7 bis, rue khaireddine pacha 1er etage",
    "telephone": "77307407",
    "ville": "kairouan"
  },
  {
    "nom": "MEJRI Souad",
    "specialité": "Médecine générale",
    "adresse": "Rue 7 novembre",
    "telephone": "77240117",
    "ville": "kairouan"
  },
  {
    "nom": "MERGHNI Seifeddine",
    "specialité": "Médecine générale",
    "adresse": "Rue de l'environnement cité el hajem",
    "telephone": "77304917",
    "ville": "kairouan"
  },
  {
    "nom": "SARSOUT Nada",
    "specialité": "Médecine générale",
    "adresse": "Groupement de Santé de Base de Ahmed Al-Qarawi à Kairouan 3100",
    "telephone": "76485376",
    "ville": "kairouan"
  },
  {
    "nom": "SIDAOUI OTHMENI Lamia",
    "specialité": "Médecine générale",
    "adresse": "HOPITAL REGIONAL IBN EL JAZZAR KAIROUAN Rue Ibn Jazzar 3100, KAIROUAN 3100",
    "telephone": "77226300",
    "ville": "kairouan"
  },
  {
    "nom": "BEN LASSOUED Anis",
    "specialité": "Chirurgie orthopédique et traumatologique",
    "adresse": "22,rue abi zomaa el balaoui diar echifaa  kairouan  3100",
    "telephone": "22523506",
    "ville": "kairouan"
  },
  {
    "nom": "TOUMI Lotfi",
    "specialité": "Médecine générale",
    "adresse": "HOPITAL CIRCONSCRIPTION CHEBIKA GP 3 3121, CHEBIKA KAIROUAN 3121",
    "telephone": "77300950",
    "ville": "kairouan"
  },
  {
    "nom": "REZGANI Taoufik",
    "specialité": "Médecine générale",
    "adresse": "Hôpital de circonscription haffouz 3100",
    "telephone": "77355022",
    "ville": "kairouan"
  },
  {
    "nom": "OUNAIS Abdelahad",
    "specialité": "Chirurgie urologique",
    "adresse": "22,rue abi zomaa el balaoui",
    "telephone": "77231424",
    "ville": "kairouan"
  },
  {
    "nom": "ABDELKEFI Fatma",
    "specialité": "Médecine générale",
    "adresse": "1 rue ali belahouane",
    "telephone": "77238045",
    "ville": "kairouan"
  },
  {
    "nom": "HAMDI Rym",
    "specialité": "Médecine générale",
    "adresse": "Nouvelle cité",
    "telephone": "77256551",
    "ville": "kairouan"
  },
  {
    "nom": "DAADOUCHA Abderrahmen",
    "specialité": "Médecine générale",
    "adresse": "HOPITAL REGIONAL IBN JAZAR KAIRAOUAN 3100",
    "telephone": "73369430",
    "ville": "kairouan"
  },
  {
    "nom": "CHENGUEL BEN JHA Ikram",
    "specialité": "Médecine générale",
    "adresse": "Polyclinique des f.s.i kairouansecteur régional de police",
    "telephone": "73304770",
    "ville": "kairouan"
  },
  {
    "nom": "MAHDOUI Afifa",
    "specialité": "Médecine générale",
    "adresse": "hôpital de circonscription bouhajla 3100",
    "telephone": "77227277",
    "ville": "kairouan"
  },
  {
    "nom": "MESSAOUDI Ahlem",
    "specialité": "Médecine générale",
    "adresse": "Groupement de santé de base HAFOUZE",
    "telephone": "77284200",
    "ville": "kairouan"
  },
  {
    "nom": "AIDI Ibrahim",
    "specialité": "Médecine générale",
    "adresse": "Hôpital cherarda",
    "telephone": "77620302",
    "ville": "kairouan"
  },
  {
    "nom": "KHEDIM Adel",
    "specialité": "Oto-rhino-laryngologie",
    "adresse": "23, avenue abou zomaa el balaoui",
    "telephone": "77232066",
    "ville": "kairouan"
  },
  {
    "nom": "BOUBAKER Hafedh",
    "specialité": "Ophtalmologie",
    "adresse": "20 rue de Carthage  kairouan  3100",
    "telephone": "77232200",
    "ville": "kairouan"
  },
  {
    "nom": "SFAR Sonia",
    "specialité": "Médecine générale",
    "adresse": "HOPITAL CIRCONSCRIPTION EL JEM Boulevard du 7 Novembre 5160, EL JEM MAHDIA 5160",
    "telephone": "77226300",
    "ville": "kairouan"
  },
  {
    "nom": "DABGHI Radhia",
    "specialité": "Médecine générale",
    "adresse": "Hôpital de circonscription nasrallah 3100",
    "telephone": "77233035",
    "ville": "kairouan"
  },
  {
    "nom": "NABLI AYACHI Hager",
    "specialité": "Médecine générale",
    "adresse": "Hôpital de circonscription BOUHAJLA Bou Hajla 3130",
    "telephone": "77266049",
    "ville": "kairouan"
  },
  {
    "nom": "KARRAY Sabeur",
    "specialité": "Médecine générale",
    "adresse": "Rue du 7 novembre",
    "telephone": "77268700",
    "ville": "kairouan"
  },
  {
    "nom": "REZGUI Kamel",
    "specialité": "Médecine générale",
    "adresse": "Route de chorbane",
    "telephone": "98591251",
    "ville": "kairouan"
  },
  {
    "nom": "TOUILI Yasser",
    "specialité": "Chirurgie urologique",
    "adresse": "Avenue télémcen",
    "telephone": "23201805",
    "ville": "kairouan"
  },
  {
    "nom": "BOUHOULA GHARSALLAH Faten",
    "specialité": "Médecine générale",
    "adresse": "Avenue ibn el aghleb",
    "telephone": "77271029",
    "ville": "kairouan"
  },
  {
    "nom": "BEN KHEDIJA Jamila",
    "specialité": "Médecine générale",
    "adresse": "Cnam",
    "telephone": "77229460",
    "ville": "kairouan"
  },
  {
    "nom": "LIOUANE Mohamed",
    "specialité": "Imagerie médicale",
    "adresse": "Av.Abi Zomaa el balaoui 3100",
    "telephone": "77237200",
    "ville": "kairouan"
  },
  {
    "nom": "DHOUIBI Essaied",
    "specialité": "Gynécologie obstétrique",
    "adresse": "Avenue beit el hekma cité med ali",
    "telephone": "77228999",
    "ville": "kairouan"
  },
  {
    "nom": "AYED Mehdi",
    "specialité": "Médecine générale",
    "adresse": "Av.Habib Bourguiba",
    "telephone": "77365501",
    "ville": "kairouan"
  },
  {
    "nom": "KHAMMARI TAKTAK Sameh",
    "specialité": "Médecine générale",
    "adresse": "HOPITAL REGIONAL IBN EL JAZZAR KAIROUAN Rue Ibn Jazzar 3100, KAIROUAN 3100",
    "telephone": "77305909",
    "ville": "kairouan"
  },
  {
    "nom": "ALOUINI MEKKI Rafika",
    "specialité": "Imagerie médicale",
    "adresse": "Direction Régional de la Santé Publique Kairouan KAIROUAN 3100",
    "telephone": "77226300",
    "ville": "kairouan"
  },
  {
    "nom": "KHELIF Abdallah",
    "specialité": "Médecine générale",
    "adresse": "Av.Abi Zamaa el balaoui -rue sidi ben gouta",
    "telephone": "25245515",
    "ville": "kairouan"
  },
  {
    "nom": "KACHOUKH JRADI Hager",
    "specialité": "Dermatologie",
    "adresse": "Rue ibn el aghleb Immeuble ibn sina",
    "telephone": "77274306",
    "ville": "kairouan"
  },
  {
    "nom": "HAMZAOUI Hichem",
    "specialité": "Médecine générale",
    "adresse": "rue Nouvelle ère Haffouz 3130",
    "telephone": "98689208",
    "ville": "kairouan"
  },
  {
    "nom": "HENI Fredj",
    "specialité": "Médecine générale",
    "adresse": "Polyclinique force sécurité intérieur",
    "telephone": "77336215",
    "ville": "kairouan"
  },
  {
    "nom": "MERZOUGUI Latifa",
    "specialité": "Médecine générale",
    "adresse": "Hôpital ibn el jazzar 3170",
    "telephone": "73226300",
    "ville": "kairouan"
  },
  {
    "nom": "BAKLOUTI TURKI Afef",
    "specialité": "Médecine générale",
    "adresse": "Hôpital ibn el jazzar 3100",
    "telephone": "77226300",
    "ville": "kairouan"
  },
  {
    "nom": "BELLARA LIOUANE Ikram",
    "specialité": "Imagerie médicale",
    "adresse": "Avenue abi zomaa el balaoui",
    "telephone": "77231152",
    "ville": "kairouan"
  },
  {
    "nom": "HENI Ayachi",
    "specialité": "Médecine générale",
    "adresse": "Rue el imam sahnoun",
    "telephone": "77240250",
    "ville": "kairouan"
  },
  {
    "nom": "ELHADJ Feteh",
    "specialité": "Médecine générale",
    "adresse": "Hôpital Farhat Hached s/ce d'urgence 3100",
    "telephone": "77229333",
    "ville": "kairouan"
  },
  {
    "nom": "JAIDANE Hédi",
    "specialité": "Médecine générale",
    "adresse": "Dar jamaia",
    "telephone": "77230157",
    "ville": "kairouan"
  },
  {
    "nom": "RAGOUBI Othmane",
    "specialité": "Médecine générale",
    "adresse": "Hôpital ibn el jazzar 3100",
    "telephone": "77226300",
    "ville": "kairouan"
  },
  {
    "nom": "MALEK Yassine",
    "specialité": "Médecine générale",
    "adresse": "Caisse nationale d'assurance maladie",
    "telephone": "77234710",
    "ville": "kairouan"
  },
  {
    "nom": "BOUKADIDA Ridha",
    "specialité": "Chirurgie orthopédique et traumatologique",
    "adresse": "Rue du fes",
    "telephone": "77237167",
    "ville": "kairouan"
  },
  {
    "nom": "BEN SLIMANE Dhouha",
    "specialité": "Pneumologie",
    "adresse": "Complexe Médical  Ibn Zohr  avenue Ibn El Aghlab",
    "telephone": "77272300",
    "ville": "kairouan"
  },
  {
    "nom": "HADJ ALI Mokhtar",
    "specialité": "Médecine générale",
    "adresse": "Hôpital regional ibn el jazzar 3100",
    "telephone": "77116300",
    "ville": "kairouan"
  },
  {
    "nom": "SAIDI Belkacem",
    "specialité": "Médecine générale",
    "adresse": "",
    "telephone": "77370488",
    "ville": "kairouan"
  },
  {
    "nom": "BARHOUMI Tarek",
    "specialité": "Médecine générale",
    "adresse": "Direction régionale de la santé publique",
    "telephone": "77286494",
    "ville": "kairouan"
  },
  {
    "nom": "FEJJI Samir",
    "specialité": "Pédiatrie",
    "adresse": "45,rue de 2 mars 1934",
    "telephone": "73233888",
    "ville": "kairouan"
  },
  {
    "nom": "MEFTAH Adel",
    "specialité": "Gynécologie obstétrique",
    "adresse": "Rue ibn el aghleb",
    "telephone": "77271666",
    "ville": "kairouan"
  },
  {
    "nom": "HASSINE Ridha",
    "specialité": "Cardiologie",
    "adresse": "Rue aicha omelmoominine",
    "telephone": "77228848",
    "ville": "kairouan"
  },
  {
    "nom": "TROUDI Monia",
    "specialité": "Pédiatrie",
    "adresse": "Rue ibn el aghleb",
    "telephone": "77234228",
    "ville": "kairouan"
  },
  {
    "nom": "ATALLAH Zouhaier",
    "specialité": "Oto-rhino-laryngologie",
    "adresse": "20,av.Abi Zomaa el balaoui",
    "telephone": "73230111",
    "ville": "kairouan"
  },
  {
    "nom": "EZZEDINI Mustapha",
    "specialité": "Médecine générale",
    "adresse": "3, rue ali ben amara",
    "telephone": "77266280",
    "ville": "kairouan"
  },
  {
    "nom": "KSOURI Monia",
    "specialité": "Médecine générale",
    "adresse": "Groupement de santé de base ahmed el karoui",
    "telephone": "77231017",
    "ville": "kairouan"
  },
  {
    "nom": "ALOUI Mohamed",
    "specialité": "Médecine générale",
    "adresse": "Hôpital cherarda",
    "telephone": "77268584",
    "ville": "kairouan"
  },
  {
    "nom": "THAALBI Rafik",
    "specialité": "Cardiologie",
    "adresse": "76 rue beyrouth cité med.ALI",
    "telephone": "77228897",
    "ville": "kairouan"
  },
  {
    "nom": "ZBIDI Abdelmajid",
    "specialité": "Médecine générale",
    "adresse": "Rue de la liberté",
    "telephone": "77268559",
    "ville": "kairouan"
  },
  {
    "nom": "LADJIMI Mohamed El Habib",
    "specialité": "Médecine générale",
    "adresse": "Avenue de la république n° 26",
    "telephone": "26156928",
    "ville": "kairouan"
  },
  {
    "nom": "SELMI Mansour",
    "specialité": "Chirurgie générale",
    "adresse": "Hôpital Ibn El jazzar KAIROUAN 3100",
    "telephone": "77226300",
    "ville": "kairouan"
  },
  {
    "nom": "ROUIS Mohamed",
    "specialité": "Médecine générale",
    "adresse": "",
    "telephone": "77226300",
    "ville": "kairouan"
  },
  {
    "nom": "ROUROU Imed",
    "specialité": "Oto-rhino-laryngologie",
    "adresse": "35 rue 2 mars 1934",
    "telephone": "77237077",
    "ville": "kairouan"
  },
  {
    "nom": "AMRI Fethi",
    "specialité": "Pédiatrie",
    "adresse": "98, avenue abou zomaa balaoui",
    "telephone": "77234423",
    "ville": "kairouan"
  },
  {
    "nom": "NEGRA Rached",
    "specialité": "Gynécologie obstétrique",
    "adresse": "21, rue ibn el aghleb imm ibn sina etage 2",
    "telephone": "98451369",
    "ville": "kairouan"
  },
  {
    "nom": "HAMOUDA Mohsen",
    "specialité": "Gynécologie obstétrique",
    "adresse": "5, avenue khaireddine becha cité hajjem",
    "telephone": "77306501",
    "ville": "kairouan"
  },
  {
    "nom": "KECHRID Maher",
    "specialité": "Imagerie médicale",
    "adresse": "Avenue ibn el aghlab immeuble  ibn sina ",
    "telephone": "77270666",
    "ville": "kairouan"
  },
  {
    "nom": "GAZZAH Habib",
    "specialité": "Neurologie",
    "adresse": "2, avenue kortoba",
    "telephone": "77226319",
    "ville": "kairouan"
  },
  {
    "nom": "GHARSALLAH Abdellatif",
    "specialité": "Anesthésie réanimation",
    "adresse": "Clinique laouani",
    "telephone": "77271444",
    "ville": "kairouan"
  },
  {
    "nom": "AMRI Lotfi",
    "specialité": "Ophtalmologie",
    "adresse": "Rue aicha oum el moomenine ouled farhane",
    "telephone": "77235605",
    "ville": "kairouan"
  },
  {
    "nom": "SOULA Tarek",
    "specialité": "Chirurgie carcinologique",
    "adresse": "Av.Abi Zomaa el balaoui 'devant galerie rabii)",
    "telephone": "77228253",
    "ville": "kairouan"
  },
  {
    "nom": "BEN ALAYA Mohamed",
    "specialité": "Imagerie médicale",
    "adresse": "Rue habib thameur  kairouan  3100",
    "telephone": "77229487",
    "ville": "kairouan"
  },
  {
    "nom": "ALOUINI Zohra",
    "specialité": "Médecine générale",
    "adresse": "Rue ahmed ibn essaraj el mansouraclidiak",
    "telephone": "77281856",
    "ville": "kairouan"
  },
  {
    "nom": "HARKI Habib",
    "specialité": "Pédiatrie",
    "adresse": "Route de kairouan",
    "telephone": "98203637",
    "ville": "kairouan"
  },
  {
    "nom": "BEN SAYEH Mohamed Malek",
    "specialité": "Chirurgie orthopédique et traumatologique",
    "adresse": "22, rue abou zomaa el balaoui",
    "telephone": "77233344",
    "ville": "kairouan"
  },
  {
    "nom": "AZIZ Fredj",
    "specialité": "Gynécologie obstétrique",
    "adresse": "3bis, rue telemcen",
    "telephone": "77228222",
    "ville": "kairouan"
  },
  {
    "nom": "TARFAOUI Chokri",
    "specialité": "Médecine générale",
    "adresse": "Groupement de santé de base ahmed el karoui 3100",
    "telephone": "77300950",
    "ville": "kairouan"
  },
  {
    "nom": "ALOUINI Souhail",
    "specialité": "Chirurgie pédiatrique",
    "adresse": "Complexe médical ibn sina, 207 avenue ibn al aghlab",
    "telephone": "77273463",
    "ville": "kairouan"
  },
  {
    "nom": "ATALLAH Mohamed",
    "specialité": "Médecine générale",
    "adresse": "2, avenue telemcen",
    "telephone": "77234715",
    "ville": "kairouan"
  },
  {
    "nom": "BEN CHARFEDDINE Faouzi",
    "specialité": "Médecine générale",
    "adresse": "Ruetaieb mhiri",
    "telephone": "77350153",
    "ville": "kairouan"
  },
  {
    "nom": "MOUISSAOUI Mahmoud",
    "specialité": "Médecine générale",
    "adresse": "Cité Hôpital cherarda 3116",
    "telephone": "99999608",
    "ville": "kairouan"
  },
  {
    "nom": "MOSBAH Moncef",
    "specialité": "Chirurgie générale",
    "adresse": "Rue hedi chaker route oueslatia",
    "telephone": "77304447",
    "ville": "kairouan"
  },
  {
    "nom": "AOUANI Mohamed Ali",
    "specialité": "Cardiologie",
    "adresse": "Rue ibn el aghlab Kairouan 3100",
    "telephone": "77271444",
    "ville": "kairouan"
  },
  {
    "nom": "KHELIF Jalel",
    "specialité": "Pédiatrie",
    "adresse": "98, av.Abi Zamaa el balaoui Kairouan 3100",
    "telephone": "77236555",
    "ville": "kairouan"
  },
  {
    "nom": "HAMMAMI Said",
    "specialité": "Médecine générale",
    "adresse": "rue 2 mars Sbikha 3110",
    "telephone": "77365059",
    "ville": "kairouan"
  },
  {
    "nom": "H'SIRA Hamouda",
    "specialité": "Médecine générale",
    "adresse": "Hôpital de ain jelloula Ain Jelloula 3113",
    "telephone": "77350001",
    "ville": "kairouan"
  },
  {
    "nom": "MISKINI Abdelhafidh",
    "specialité": "Médecine générale",
    "adresse": "Avenue habib thameur Kairouan 3180",
    "telephone": "77266188",
    "ville": "kairouan"
  },
  {
    "nom": "GAALICHE Souleim",
    "specialité": "Médecine générale",
    "adresse": "Hôpital régional de msaken circonscription sanitaire 4002-Sousse Bouhssina 4070",
    "telephone": "77226300",
    "ville": "kairouan"
  },
  {
    "nom": "SAIDI Sassi",
    "specialité": "Médecine générale",
    "adresse": "9, rue monastir Hajeb Ayoun 3160",
    "telephone": "77370350",
    "ville": "kairouan"
  },
  {
    "nom": "DHIFAOUI Mohamed Naceur",
    "specialité": "Médecine générale",
    "adresse": "Rue aouled haffouz Bouhajla 3180",
    "telephone": "77266290",
    "ville": "kairouan"
  },
  {
    "nom": "TEKAYA Abdeladhim",
    "specialité": "Gynécologie obstétrique",
    "adresse": "2 rue essakia Kairouan 3100",
    "telephone": "77229545",
    "ville": "kairouan"
  },
  {
    "nom": "HMAYER Slaheddine",
    "specialité": "Dermatologie",
    "adresse": "Rue du 3 septembre Kairouan 3100",
    "telephone": "77232088",
    "ville": "kairouan"
  },
  {
    "nom": "GHILENE Abdelaziz",
    "specialité": "Médecine générale",
    "adresse": "avenue Ibn El Jazzar Kairouan 3100",
    "telephone": "53751271",
    "ville": "kairouan"
  },
  {
    "nom": "BEN OTHMAN Hafedh",
    "specialité": "Médecine générale",
    "adresse": "Direction régional de la santé Kairouan 3100",
    "telephone": "77286494",
    "ville": "kairouan"
  },
  {
    "nom": "MRABET Amel",
    "specialité": "Médecine générale",
    "adresse": "Groupement de santé de base  ahmed El Karoui  Kairouan 3100",
    "telephone": "77235176",
    "ville": "kairouan"
  },
  {
    "nom": "ZAIER SGHAIER Rafika",
    "specialité": "Médecine générale",
    "adresse": "Groupement de santé de base ahmed el karoui Kairouan 3110",
    "telephone": "77305011",
    "ville": "kairouan"
  },
  {
    "nom": "BEN NASR Rachid",
    "specialité": "Oto-rhino-laryngologie",
    "adresse": "Avenue abou zomaa el balaoui Kairouan 3100",
    "telephone": "23596386",
    "ville": "kairouan"
  },
  {
    "nom": "SELLAMI Abderraouf",
    "specialité": "Ophtalmologie",
    "adresse": "9 bis rue 20 mars bab jalladine Kairouan 3100",
    "telephone": "77230364",
    "ville": "kairouan"
  },
  {
    "nom": "AYACHI Taieb",
    "specialité": "Médecine générale",
    "adresse": "08, avenue touhami negra Kairouan 3100",
    "telephone": "77272272",
    "ville": "kairouan"
  },
  {
    "nom": "ATALLAH Mohamed Rachid",
    "specialité": "Psychiatrie",
    "adresse": "Hôpital ibn el jazzar 3100",
    "telephone": "77226300",
    "ville": "kairouan"
  },
  {
    "nom": "ESSBOUI Samir",
    "specialité": "Médecine générale",
    "adresse": "direction régional de la sante KAIROUAN 3100",
    "telephone": "72676333",
    "ville": "kairouan"
  },
  {
    "nom": "HARRATHI Ali",
    "specialité": "Médecine générale",
    "adresse": "Avenue de l'environnement cité hajjem Kairouan 3100",
    "telephone": "73301373",
    "ville": "kairouan"
  },
  {
    "nom": "KHARRAT Mohamed Lanouar",
    "specialité": "Médecine générale",
    "adresse": "Rue ibn el jazzar place tunis El Mansoura 3100",
    "telephone": "77237999",
    "ville": "kairouan"
  },
  {
    "nom": "N'FOUKI Abdelkrim",
    "specialité": "Médecine générale",
    "adresse": "Route de haffouz cité okba Kairouan 3100",
    "telephone": "97373010",
    "ville": "kairouan"
  },
  {
    "nom": "KRAIEM Mohamed",
    "specialité": "Médecine générale",
    "adresse": "Rue Mohamed Negra Kairouan 3100",
    "telephone": "77271486",
    "ville": "kairouan"
  },
  {
    "nom": "ANNABI Mohamed",
    "specialité": "Médecine générale",
    "adresse": "13, cité ennasr Hajeb El Ayoun 3160",
    "telephone": "77370248",
    "ville": "kairouan"
  },
  {
    "nom": "AMRI Samir",
    "specialité": "Médecine générale",
    "adresse": "Av.Ali Belhavan Kairouan 3100",
    "telephone": "77229708",
    "ville": "kairouan"
  },
  {
    "nom": "DHOUIBI Salah",
    "specialité": "Médecine générale",
    "adresse": "Av.Beit El hikma Kairouan 3100",
    "telephone": "77 23 26 11",
    "ville": "kairouan"
  },
  {
    "nom": "KECHRID Adel",
    "specialité": "Médecine générale",
    "adresse": "GP3 AIN BIDHA Haffouz 3180",
    "telephone": "21436362",
    "ville": "kairouan"
  },
  {
    "nom": "BEN ZINA Mohamed Néjib",
    "specialité": "Ophtalmologie",
    "adresse": "Cité commerciale 2 Kairouan 3100",
    "telephone": "77233144",
    "ville": "kairouan"
  },
  {
    "nom": "DHIB Hamadi",
    "specialité": "Pneumologie",
    "adresse": "Cité commerciale 2 app n° 7 Kairouan 3100",
    "telephone": "77231141",
    "ville": "kairouan"
  },
  {
    "nom": "AMARA Abdelwahab",
    "specialité": "Médecine générale",
    "adresse": "Rue mosquée el warda hay el ansar Kairouan 3100",
    "telephone": "77232750",
    "ville": "kairouan"
  },
  {
    "nom": "EL BLAIECH Khaled",
    "specialité": "Médecine générale",
    "adresse": "Avenue beit el hekma cité mansourah Kairouan 3100",
    "telephone": "77233114",
    "ville": "kairouan"
  },
  {
    "nom": "BEL KNANI Rachid",
    "specialité": "Médecine générale",
    "adresse": "Avenue Ibn Aghlab Kairouan 3100",
    "telephone": "77288226",
    "ville": "kairouan"
  },
  {
    "nom": "MANAA ROMDHANE Najet",
    "specialité": "Médecine générale",
    "adresse": "6, rue m.ibn badis Kairouan 3100",
    "telephone": "77226345",
    "ville": "kairouan"
  },
  {
    "nom": "MEJRI Habib",
    "specialité": "Médecine générale",
    "adresse": "Rue ibn el jazzar Hajeb El Ayoun 3160",
    "telephone": "77371102",
    "ville": "kairouan"
  },
  {
    "nom": "ALLANI Chokri",
    "specialité": "Médecine générale",
    "adresse": "Cité commerciale el hajjem Kairouan 3100",
    "telephone": "77302511",
    "ville": "kairouan"
  },
  {
    "nom": "AMMAR Habib",
    "specialité": "Médecine générale",
    "adresse": "Rue kaid ajimi Bouhajla 3180",
    "telephone": "77166046",
    "ville": "kairouan"
  },
  {
    "nom": "SOLTANE Mohamed",
    "specialité": "Médecine générale",
    "adresse": "Kairouan 3100",
    "telephone": "77226817",
    "ville": "kairouan"
  },
  {
    "nom": "GHEDIRA Fathi",
    "specialité": "Médecine générale",
    "adresse": "Rue ibn el jazzar Kairouan 3100",
    "telephone": "77232828",
    "ville": "kairouan"
  },
  {
    "nom": "MEFTAH Ali",
    "specialité": "Médecine générale",
    "adresse": "Rue el abassia Kairouan 3100",
    "telephone": "77273939",
    "ville": "kairouan"
  },
  {
    "nom": "BEN ALAYA Mohamed Fethi",
    "specialité": "Médecine générale",
    "adresse": "Rue abi zomâa el balaoui imm.Dar Echifa Kairouan 3100",
    "telephone": "77231234",
    "ville": "kairouan"
  },
  {
    "nom": "SOUA MEFTAH Amel",
    "specialité": "Gynécologie obstétrique",
    "adresse": "En face maison des juges sahbi 4 Kairouan 3100",
    "telephone": "77272299",
    "ville": "kairouan"
  },
  {
    "nom": "DJEBENIANI Badreddine",
    "specialité": "Médecine générale",
    "adresse": "Rue farhat hached 3180",
    "telephone": "77266063",
    "ville": "kairouan"
  },
  {
    "nom": "SADFI Radhouane",
    "specialité": "Gastro-entérologie",
    "adresse": "Avenue abi zoumaâ balaoui Kairouan 3100",
    "telephone": "77228811",
    "ville": "kairouan"
  },
  {
    "nom": "MTIRI Ali",
    "specialité": "Gastro-entérologie",
    "adresse": "Rue mouaouia ibn houdaiej cite el hajjam Kairouan 3100",
    "telephone": "77301915",
    "ville": "kairouan"
  },
  {
    "nom": "OUERTANI Mohamed",
    "specialité": "Endocrinologie",
    "adresse": "Rue khémaies ternane Kairouan Okba 3100",
    "telephone": "77301509",
    "ville": "kairouan"
  },
  {
    "nom": "NSIRI Hamadi",
    "specialité": "Médecine générale",
    "adresse": "Rue s.bent el houcine Kairouan 3100",
    "telephone": "77230907",
    "ville": "kairouan"
  },
  {
    "nom": "KEFI Nader",
    "specialité": "Médecine générale",
    "adresse": "Cité hajjam Kairouan 3100",
    "telephone": "77300365",
    "ville": "kairouan"
  },
  {
    "nom": "KHECHINE Mohamed Lotfi",
    "specialité": "Médecine générale",
    "adresse": "Rue ibrahim ibn elaghlab Kairouan 3100",
    "telephone": "77270886",
    "ville": "kairouan"
  },
  {
    "nom": "KHELIF Mohamed",
    "specialité": "Médecine générale",
    "adresse": "46 av.Abou.Z.el balaoui Kairouan 3100",
    "telephone": "77228844",
    "ville": "kairouan"
  },
  {
    "nom": "ABDELKEFI Abdelatif",
    "specialité": "Médecine générale",
    "adresse": "Centre commercial Kairouan 3100",
    "telephone": "77231381",
    "ville": "kairouan"
  },
  {
    "nom": "BEN MAHMOUD Riadh",
    "specialité": "Gynécologie obstétrique",
    "adresse": "Rue oum kalthoum lot afh sidi sahbi i Kairouan 3100",
    "telephone": "77304994",
    "ville": "kairouan"
  },
  {
    "nom": "GHARBI Lyes",
    "specialité": "Médecine générale",
    "adresse": "3110-sbikha Sbikha 3110",
    "telephone": "77365011",
    "ville": "kairouan"
  },
  {
    "nom": "KHARRAT Habib",
    "specialité": "Pédiatrie",
    "adresse": "Rue mahmoud abdellah Kairouan 3100",
    "telephone": "77232777",
    "ville": "kairouan"
  },
  {
    "nom": "BOUALLEGUE Chedly",
    "specialité": "Cardiologie",
    "adresse": "12 rue el abassia Kairouan 3100",
    "telephone": "77231400",
    "ville": "kairouan"
  },
  {
    "nom": "MAZEH Fouad",
    "specialité": "Médecine générale",
    "adresse": "Rue de damas Kairouan 3100",
    "telephone": "77230403",
    "ville": "kairouan"
  },
  {
    "nom": "MEFTAH Rachid",
    "specialité": "Médecine générale",
    "adresse": "Avenue ibn aghleb Kairouan 3100",
    "telephone": "77234914",
    "ville": "kairouan"
  },
  {
    "nom": "EL GHALI Brahim",
    "specialité": "Pédiatrie",
    "adresse": "3100",
    "telephone": "73302865",
    "ville": "kairouan"
  },
  {
    "nom": "HANAFI Hamadi",
    "specialité": "Médecine générale",
    "adresse": "37 av.Abou Z.el balaoui 3100-Kairouan 3100",
    "telephone": "77230971",
    "ville": "kairouan"
  },
  {
    "nom": "FAIZ Abdelhamid",
    "specialité": "Médecine générale",
    "adresse": "Rue m.ibn badis Kairouan 3100",
    "telephone": "77230538",
    "ville": "kairouan"
  },
  {
    "nom": "ZONE Bouraoui",
    "specialité": "Pédiatrie",
    "adresse": "Mahdia 3100",
    "telephone": "73692564",
    "ville": "kairouan"
  },
  {
    "nom": "RAMADAN Mohamed Ayman",
    "specialité": "Médecine générale",
    "adresse": "6 rue m.ibn badis Kairouan 3100",
    "telephone": "77228447",
    "ville": "kairouan"
  },
  {
    "nom": "ALAYOUBI Fadi",
    "specialité": "Médecine générale",
    "adresse": "Rue kaied ajimi Bouhajla 3180",
    "telephone": "77266151",
    "ville": "kairouan"
  },
  {
    "nom": "ARABI Hayssam",
    "specialité": "Médecine générale",
    "adresse": "El baten Kairouan 3142",
    "telephone": "23022661",
    "ville": "kairouan"
  }
]
